LICENSE
README
setup.py
DingRobotPy.egg-info/PKG-INFO
DingRobotPy.egg-info/SOURCES.txt
DingRobotPy.egg-info/dependency_links.txt
DingRobotPy.egg-info/requires.txt
DingRobotPy.egg-info/top_level.txt
dingbot/Card.py
dingbot/__init__.py