Metadata-Version: 2.1
Name: DingRobotPy
Version: 3.75.0
Summary: Dingtalk group's robot API Python SDK
Home-page: https://github.com/WuJunkai2004/Dingbot
Download-URL: https://github.com/WuJunkai2004/Dingbot
Author: WuJunkai
Author-email: wujunkai20041123@outlook.com
Classifier: Development Status :: 5 - Production/Stable
Classifier: Environment :: Web Environment
Classifier: Intended Audience :: Developers
Classifier: License :: OSI Approved :: MIT License
Classifier: Operating System :: OS Independent
Classifier: Programming Language :: Python
Classifier: Topic :: Internet
Classifier: Topic :: Software Development :: Libraries :: Python Modules
License-File: LICENSE
